Metadata-Version: 2.1
Name: imraylib
Version: 1.0.0
Summary: Integrates Imgui with Raylib
Home-page: https://github.com/adamlwgriffiths/imraylib/
Author: Adam Griffiths
Author-email: adam.lw.griffiths@gmail.com
License: BSD 3-Clause License
Platform: UNKNOWN
Classifier: Intended Audience :: Developers
Classifier: License :: OSI Approved :: BSD License
Classifier: Operating System :: OS Independent
Classifier: Programming Language :: Python
Classifier: Programming Language :: Python :: 3
Classifier: Topic :: Multimedia :: Graphics
Classifier: Topic :: Software Development :: Libraries :: Python Modules
Requires-Python: >=3.4
